lti13oauthenticator/__init__.py
lti13oauthenticator/_version.py
lti13oauthenticator/lti13.py
lti13oauthenticator-0.1.0.dist-info/METADATA
lti13oauthenticator-0.1.0.dist-info/WHEEL
lti13oauthenticator-0.1.0.dist-info/entry_points.txt
lti13oauthenticator-0.1.0.dist-info/top_level.txt
lti13oauthenticator-0.1.0.dist-info/RECORD
