Metadata-Version: 2.1
Name: lti13oauthenticator
Version: 0.1.0
Summary: LTI13OAuthenticator: Authenticate JupyterHub users with common LTI1.3 providers
Home-page: https://jupyter.org
Author: Jupyter Development Team
Author-email: jupyter@googlegroups.com
License: BSD
Keywords: Interactive,Interpreter,Shell,Web
Platform: Linux
Platform: Mac OS X
Classifier: Intended Audience :: Developers
Classifier: Intended Audience :: System Administrators
Classifier: Intended Audience :: Science/Research
Classifier: License :: OSI Approved :: BSD License
Classifier: Programming Language :: Python
Classifier: Programming Language :: Python :: 3
Requires-Python: >=3.6
Requires-Dist: jupyterhub (>=0.5)
Requires-Dist: oauthenticator (>0.12)
Requires-Dist: pyjwt
